[{"__type__":"cc.Prefab","_name":"quickPhraseItem","data":{"__id__":1}},{"__type__":"cc.Node","_name":"item","_level":1,"_components":[{"__type__":"cc.Label","node":{"__id__":1},"_srcBlendFactor":1,"_useOriginalSize":false,"_string":"快点啊，都等到我花儿都谢谢了！","_N$string":"快点啊，都等到我花儿都谢谢了！","_fontSize":30,"_lineHeight":30,"_N$horizontalAlign":1}],"_prefab":{"__type__":"cc.PrefabInfo","root":{"__id__":1},"asset":{"__uuid__":"831PrlvQlFpoW73lS+ycNO"},"fileId":"43LjLv97FGD6CAnnotb/Ny"},"_color":{"__type__":"cc.Color"},"_contentSize":{"__type__":"cc.Size","width":450,"height":30},"_anchorPoint":{"__type__":"cc.Vec2","y":1},"_position":{"__type__":"cc.Vec3","x":-355},"_scale":{"__type__":"cc.Vec3","x":1,"y":1,"z":1}}]